{"frameRate":24,"name":"intro8ball","version":"5.5","compatibleVersion":"5.5","armature":[{"type":"Armature","frameRate":24,"name":"IntroTextItem","aabb":{"x":-24.5,"y":-24.5,"width":49,"height":49},"bone":[{"name":"root"}],"slot":[{"name":"icon_pen","parent":"root"}],"skin":[{"slot":[{"name":"icon_pen","display":[{"name":"icon_pen"}]}]}],"animation":[{"duration":0,"playTimes":0,"name":"animtion0"}],"defaultActions":[{"gotoAndPlay":"animtion0"}]},{"type":"Armature","frameRate":24,"name":"IntroAvatar","aabb":{"x":-44,"y":-56,"width":88,"height":112},"bone":[{"name":"root"}],"slot":[{"displayIndex":8,"name":"user_icon","parent":"root"}],"skin":[{"slot":[{"name":"user_icon","display":[{"name":"users_icons/user_1"},{"name":"users_icons/user_2"},{"name":"users_icons/user_3"},{"name":"users_icons/user_4"},{"name":"users_icons/user_5"},{"name":"users_icons/user_6"},{"name":"users_icons/computer_easy"},{"name":"users_icons/computer_medium"},{"name":"users_icons/computer_hard"}]}]}],"animation":[{"duration":0,"playTimes":0,"name":"animtion0"}],"defaultActions":[{"gotoAndPlay":"animtion0"}]},{"type":"Armature","frameRate":24,"name":"IntroPortrait","aabb":{"x":-587,"y":-112.5,"width":995,"height":706.5},"bone":[{"name":"root","transform":{"y":294}}],"slot":[{"name":"icon_setting","parent":"root"},{"name":"Difficulty1","parent":"root"},{"name":"Difficulty2","parent":"root"},{"name":"Difficulty0","parent":"root"},{"name":"Call8Off","parent":"root"},{"name":"Call8On","parent":"root"},{"name":"PlayButton","parent":"root"},{"name":"SettingsButton","parent":"root"},{"name":"IntroTopText","parent":"root"}],"skin":[{"slot":[{"name":"IntroTopText","display":[{"type":"armature","name":"IntroTextItem","transform":{"x":0.82,"y":-382}}]},{"name":"Difficulty2","display":[{"type":"armature","name":"CtrCompSelect","transform":{"x":284,"y":-198,"scX":1.19,"scY":1.19}}]},{"name":"Difficulty1","display":[{"type":"armature","name":"CtrCompSelect","transform":{"y":-198,"scX":1.19,"scY":1.1935}}]},{"name":"icon_setting","display":[{"name":"icon_setting","transform":{"x":-153,"y":151.6,"scX":1.4,"scY":1.4}}]},{"name":"Call8On","display":[{"type":"armature","name":"IntroCheckOn","transform":{"x":-271.98,"y":267.86}}]},{"name":"Call8Off","display":[{"type":"armature","name":"IntroCheckOff","transform":{"x":-272,"y":268}}]},{"name":"SettingsButton","display":[{"type":"armature","name":"IntroBtn1","transform":{"y":152,"scX":1.25,"scY":1.25}}]},{"name":"Difficulty0","display":[{"type":"armature","name":"CtrCompSelect","transform":{"x":-284,"y":-198,"scX":1.19,"scY":1.19}}]},{"name":"PlayButton","display":[{"type":"armature","name":"IntroBtn2","transform":{"y":20,"scX":1.25,"scY":1.25}}]}]}],"animation":[{"duration":0,"playTimes":0,"name":"animtion0"}],"defaultActions":[{"gotoAndPlay":"animtion0"}]},{"type":"Armature","frameRate":24,"name":"IntroBtnArrow","aabb":{"x":-140.38,"y":-64,"width":208,"height":128},"bone":[{"name":"root"}],"slot":[{"name":"over","parent":"root"},{"name":"up","parent":"root"},{"name":"hitArea","parent":"root","color":{"aM":0}}],"skin":[{"slot":[{"name":"over","display":[{"name":"popups/arrow"}]},{"name":"hitArea","display":[{"name":"popups/button_small","transform":{"x":-36.38,"scX":0.6,"scY":0.6}}]},{"name":"up","display":[{"name":"popups/arrow"}]}]}],"animation":[{"duration":0,"playTimes":0,"name":"animtion0"}],"defaultActions":[{"gotoAndPlay":"animtion0"}]},{"type":"Armature","frameRate":24,"name":"IntroBtnListBack","aabb":{"x":-144,"y":-55,"width":288,"height":110},"bone":[{"name":"root"}],"slot":[{"name":"hitArea","parent":"root","color":{"aM":0}},{"name":"over","parent":"root"},{"name":"up","parent":"root"}],"skin":[{"slot":[{"name":"over","display":[{"name":"popups/button2_hover"}]},{"name":"hitArea","display":[{"name":"popups/button2"}]},{"name":"up","display":[{"name":"popups/button2"}]}]}],"animation":[{"duration":0,"playTimes":0,"name":"animtion0"}],"defaultActions":[{"gotoAndPlay":"animtion0"}]},{"type":"Armature","frameRate":24,"name":"IntroBtnList","bone":[{"name":"root"}],"slot":[{"name":"back","parent":"root"},{"name":"next","parent":"root"},{"name":"prev","parent":"root"}],"skin":[{"slot":[{"name":"prev","display":[{"type":"armature","name":"IntroBtnArrow","transform":{"x":-100,"scX":-1}}]},{"name":"next","display":[{"type":"armature","name":"IntroBtnArrow","transform":{"x":100}}]},{"name":"back","display":[{"type":"armature","name":"IntroBtnListBack"}]}]}],"animation":[{"duration":0,"playTimes":0,"name":"animtion0"}],"defaultActions":[{"gotoAndPlay":"animtion0"}]},{"type":"Armature","frameRate":24,"name":"IntroItemText","aabb":{"x":-24.5,"y":-24.5,"width":49,"height":49},"bone":[{"name":"root"}],"slot":[{"name":"icon_pen","parent":"root"}],"skin":[{"slot":[{"name":"icon_pen","display":[{"name":"icon_pen"}]}]}],"animation":[{"duration":0,"playTimes":0,"name":"animtion0"}],"defaultActions":[{"gotoAndPlay":"animtion0"}]},{"type":"Armature","frameRate":24,"name":"IntroCheckOn","aabb":{"x":-29,"y":-32,"width":351,"height":64},"bone":[{"name":"root"}],"slot":[{"name":"up","parent":"root"},{"name":"over","parent":"root"},{"name":"hitArea","parent":"root","color":{"aM":0}}],"skin":[{"slot":[{"name":"hitArea","display":[{"name":"bg_button","transform":{"x":280,"scX":7.5}}]},{"name":"over","display":[{"name":"checkbox_1"}]},{"name":"up","display":[{"name":"checkbox_1"}]}]}],"animation":[{"duration":0,"playTimes":0,"name":"animtion0"}],"defaultActions":[{"gotoAndPlay":"animtion0"}]},{"type":"Armature","frameRate":24,"name":"IntroCheckOff","aabb":{"x":-29,"y":-32,"width":351,"height":64},"bone":[{"name":"root"}],"slot":[{"name":"up","parent":"root"},{"name":"over","parent":"root"},{"name":"hitArea","parent":"root","color":{"aM":0}}],"skin":[{"slot":[{"name":"hitArea","display":[{"name":"bg_button","transform":{"x":280,"scX":7.5}}]},{"name":"over","display":[{"name":"checkbox"}]},{"name":"up","display":[{"name":"checkbox"}]}]}],"animation":[{"duration":0,"playTimes":0,"name":"animtion0"}],"defaultActions":[{"gotoAndPlay":"animtion0"}]},{"type":"Armature","frameRate":24,"name":"IntroBtn1","aabb":{"x":-170.5,"y":-52,"width":341,"height":104},"bone":[{"name":"root"}],"slot":[{"name":"hitArea","parent":"root","color":{"aM":0}},{"name":"up","parent":"root"},{"name":"over","parent":"root"}],"skin":[{"slot":[{"name":"hitArea","display":[{"name":"popups/button3"}]},{"name":"over","display":[{"name":"popups/button3_hover"}]},{"name":"up","display":[{"name":"popups/button3"}]}]}],"animation":[{"duration":0,"playTimes":0,"name":"animtion0"}],"defaultActions":[{"gotoAndPlay":"animtion0"}]},{"type":"Armature","frameRate":24,"name":"IntroBtn2","aabb":{"x":-170.5,"y":-52,"width":341,"height":104},"bone":[{"name":"root"}],"slot":[{"name":"hitArea","parent":"root","color":{"aM":0}},{"name":"up","parent":"root"},{"name":"over","parent":"root"}],"skin":[{"slot":[{"name":"over","display":[{"name":"popups/button4_hover"}]},{"name":"up","display":[{"name":"popups/button4"}]},{"name":"hitArea","display":[{"name":"popups/button4"}]}]}],"animation":[{"duration":0,"playTimes":0,"name":"animtion0"}],"defaultActions":[{"gotoAndPlay":"animtion0"}]},{"type":"Armature","frameRate":24,"name":"CtrCompSelect","aabb":{"x":-124,"y":-124,"width":248,"height":248},"bone":[{"name":"root"}],"slot":[{"name":"hitArea","parent":"root","color":{"aM":0}},{"name":"up","parent":"root","color":{"aM":0}},{"name":"over","parent":"root"},{"name":"border","parent":"root"},{"name":"Avatar","parent":"root"},{"name":"WinLose","parent":"root"},{"name":"Difficulty","parent":"root"}],"skin":[{"slot":[{"name":"hitArea","display":[{"name":"popups/color","transform":{"scX":5.5,"scY":5.5}}]},{"name":"Difficulty","display":[{"type":"armature","name":"IntroTextItem","transform":{"y":38}}]},{"name":"WinLose","display":[{"type":"armature","name":"IntroTextItem","transform":{"y":78}}]},{"name":"up","display":[{"name":"popups/color"}]},{"name":"Avatar","display":[{"type":"armature","name":"IntroAvatar","transform":{"y":-42}}]},{"name":"border","display":[{"name":"popups/border_user"}]},{"name":"over","display":[{"name":"popups/border_user"}]}]}],"animation":[{"duration":0,"playTimes":0,"name":"prev2"}],"defaultActions":[{"gotoAndPlay":"prev2"}]},{"type":"Armature","frameRate":24,"name":"IntroLandscape","aabb":{"x":-559,"y":-260,"width":939,"height":696},"bone":[{"name":"root","transform":{"y":12}}],"slot":[{"name":"glow_bg","parent":"root"},{"name":"icon_settings","parent":"root"},{"name":"Difficulty1","parent":"root"},{"name":"Difficulty0","parent":"root"},{"name":"Difficulty2","parent":"root"},{"name":"Call8Off","parent":"root"},{"name":"Call8On","parent":"root"},{"name":"PlayButton","parent":"root"},{"name":"SettingsButton","parent":"root"},{"name":"IntroTopText","parent":"root"}],"skin":[{"slot":[{"name":"Call8On","display":[{"type":"armature","name":"IntroCheckOn","transform":{"x":-244,"y":392}}]},{"name":"Call8Off","display":[{"type":"armature","name":"IntroCheckOff","transform":{"x":-244,"y":392}}]},{"name":"Difficulty2","display":[{"type":"armature","name":"CtrCompSelect","transform":{"x":256,"y":126}}]},{"name":"Difficulty0","display":[{"type":"armature","name":"CtrCompSelect","transform":{"x":-256,"y":126}}]},{"name":"glow_bg","display":[{"name":"popups/glow_bg","transform":{"y":-170,"scX":6,"scY":4}}]},{"name":"Difficulty1","display":[{"type":"armature","name":"CtrCompSelect","transform":{"y":126}}]},{"name":"IntroTopText","display":[{"type":"armature","name":"IntroTextItem","transform":{"y":-24}}]},{"name":"icon_settings","display":[{"name":"popups/icon_settings","transform":{"x":74,"y":302.68}}]},{"name":"SettingsButton","display":[{"type":"armature","name":"IntroBtn1","transform":{"x":200,"y":300}}]},{"name":"PlayButton","display":[{"type":"armature","name":"IntroBtn2","transform":{"x":-200,"y":300}}]}]}],"animation":[{"duration":0,"playTimes":0,"name":"animtion0"}],"defaultActions":[{"gotoAndPlay":"animtion0"}]},{"type":"Armature","frameRate":24,"name":"WebGlError","aabb":{"x":-24.5,"y":123.5,"width":49,"height":49},"bone":[{"name":"root"}],"slot":[{"name":"IntroTopText","parent":"root"}],"skin":[{"slot":[{"name":"IntroTopText","display":[{"type":"armature","name":"IntroTextItem","transform":{"y":148,"scX":1.25,"scY":1.25}}]}]}],"animation":[{"duration":0,"playTimes":0,"name":"animtion0"}],"defaultActions":[{"gotoAndPlay":"animtion0"}]}]}