{
"layoutname":"Strongroom",
"v1":5,
"p1":[5,6],
"v2":5,
"p2":[7,6],
"v3":5,
"p3":[10,6],
"v4":5,
"p4":[12,6],
"v5":5,
"p5":[18,6],
"v6":5,
"p6":[20,6],
"v7":5,
"p7":[23,6],
"v8":5,
"p8":[25,6],
"v9":4,
"p9":[6,8],
"v10":4,
"p10":[5,6],
"v11":4,
"p11":[8,8],
"v12":4,
"p12":[6,4],
"v13":4,
"p13":[9,6],
"v14":4,
"p14":[8,4],
"v15":4,
"p15":[11,6],
"v16":4,
"p16":[14,8],
"v17":4,
"p17":[13,6],
"v18":4,
"p18":[16,8],
"v19":4,
"p19":[14,4],
"v20":4,
"p20":[17,6],
"v21":4,
"p21":[16,4],
"v22":4,
"p22":[19,6],
"v23":4,
"p23":[22,8],
"v24":4,
"p24":[21,6],
"v25":4,
"p25":[24,8],
"v26":4,
"p26":[22,4],
"v27":4,
"p27":[25,6],
"v28":4,
"p28":[24,4],
"v29":3,
"p29":[8,12],
"v30":3,
"p30":[5,8],
"v31":3,
"p31":[5,6],
"v32":3,
"p32":[7,8],
"v33":3,
"p33":[5,4],
"v34":3,
"p34":[9,8],
"v35":3,
"p35":[13,12],
"v36":3,
"p36":[7,4],
"v37":3,
"p37":[9,6],
"v38":3,
"p38":[9,4],
"v39":3,
"p39":[13,8],
"v40":3,
"p40":[17,12],
"v41":3,
"p41":[13,6],
"v42":3,
"p42":[15,8],
"v43":3,
"p43":[13,4],
"v44":3,
"p44":[17,8],
"v45":3,
"p45":[15,4],
"v46":3,
"p46":[17,6],
"v47":3,
"p47":[22,12],
"v48":3,
"p48":[17,4],
"v49":3,
"p49":[21,8],
"v50":3,
"p50":[21,6],
"v51":3,
"p51":[23,8],
"v52":3,
"p52":[21,4],
"v53":3,
"p53":[25,8],
"v54":3,
"p54":[23,4],
"v55":3,
"p55":[25,6],
"v56":3,
"p56":[25,4],
"v57":2,
"p57":[5,13],
"v58":2,
"p58":[5,11],
"v59":2,
"p59":[7,13],
"s59":"multiplier",
"v60":2,
"p60":[7,11],
"v61":2,
"p61":[9,13],
"v62":2,
"p62":[5,8],
"v63":2,
"p63":[9,11],
"v64":2,
"p64":[5,6],
"v65":2,
"p65":[7,8],
"v66":2,
"p66":[12,13],
"v67":2,
"p67":[5,4],
"v68":2,
"p68":[9,8],
"v69":2,
"p69":[12,11],
"v70":2,
"p70":[14,13],
"v71":2,
"p71":[7,4],
"v72":2,
"p72":[9,6],
"v73":2,
"p73":[14,11],
"s73":"multiplier",
"v74":2,
"p74":[16,13],
"s74":"multiplier",
"v75":2,
"p75":[9,4],
"v76":2,
"p76":[13,8],
"s76":"multiplier",
"v77":2,
"p77":[16,11],
"v78":2,
"p78":[18,13],
"v79":2,
"p79":[13,6],
"v80":2,
"p80":[15,8],
"v81":2,
"p81":[18,11],
"v82":2,
"p82":[21,13],
"v83":2,
"p83":[13,4],
"s83":"multiplier",
"v84":2,
"p84":[17,8],
"s84":"multiplier",
"v85":2,
"p85":[21,11],
"v86":2,
"p86":[23,13],
"v87":2,
"p87":[15,4],
"v88":2,
"p88":[17,6],
"v89":2,
"p89":[23,11],
"s89":"multiplier",
"v90":2,
"p90":[25,13],
"v91":2,
"p91":[17,4],
"s91":"multiplier",
"v92":2,
"p92":[21,8],
"v93":2,
"p93":[25,11],
"v94":2,
"p94":[21,6],
"v95":2,
"p95":[23,8],
"v96":2,
"p96":[21,4],
"v97":2,
"p97":[25,8],
"v98":2,
"p98":[23,4],
"v99":2,
"p99":[25,6],
"v100":2,
"p100":[25,4],
"v101":1,
"p101":[5,13],
"v102":1,
"p102":[5,11],
"v103":1,
"p103":[7,13],
"v104":1,
"p104":[7,11],
"v105":1,
"p105":[9,13],
"s105":"time",
"v106":1,
"p106":[5,8],
"v107":1,
"p107":[9,11],
"v108":1,
"p108":[5,6],
"v109":1,
"p109":[7,8],
"v110":1,
"p110":[12,13],
"v111":1,
"p111":[5,4],
"v112":1,
"p112":[7,6],
"s112":"yinyang",
"v113":1,
"p113":[9,8],
"v114":1,
"p114":[12,11],
"s114":"time",
"v115":1,
"p115":[14,13],
"v116":1,
"p116":[7,4],
"v117":1,
"p117":[9,6],
"v118":1,
"p118":[14,11],
"v119":1,
"p119":[16,13],
"v120":1,
"p120":[9,4],
"v121":1,
"p121":[13,8],
"v122":1,
"p122":[16,11],
"v123":1,
"p123":[18,13],
"v124":1,
"p124":[13,6],
"v125":1,
"p125":[15,8],
"v126":1,
"p126":[18,11],
"s126":"time",
"v127":1,
"p127":[21,13],
"s127":"time",
"v128":1,
"p128":[13,4],
"v129":1,
"p129":[17,8],
"v130":1,
"p130":[21,11],
"v131":1,
"p131":[23,13],
"v132":1,
"p132":[15,4],
"v133":1,
"p133":[17,6],
"v134":1,
"p134":[23,11],
"v135":1,
"p135":[25,13],
"v136":1,
"p136":[17,4],
"v137":1,
"p137":[21,8],
"v138":1,
"p138":[25,11],
"v139":1,
"p139":[21,6],
"v140":1,
"p140":[23,8],
"v141":1,
"p141":[21,4],
"v142":1,
"p142":[23,6],
"s142":"yinyang",
"v143":1,
"p143":[25,8],
"v144":1,
"p144":[23,4],
"v145":1,
"p145":[25,6],
"v146":1,
"p146":[25,4],
"v147":1,
"p147":[3,4],
"s147":"wall",
"v148":1,
"p148":[3,6],
"s148":"wall",
"v149":1,
"p149":[3,8],
"s149":"wall",
"v150":1,
"p150":[3,11],
"s150":"wall",
"v151":1,
"p151":[3,13],
"s151":"wall",
"v152":1,
"p152":[27,4],
"s152":"wall",
"v153":1,
"p153":[27,6],
"s153":"wall",
"v154":1,
"p154":[27,8],
"s154":"wall",
"v155":1,
"p155":[27,11],
"s155":"wall",
"v156":1,
"p156":[27,13],
"s156":"wall"
}